MANIFEST.in
README.rst
setup.cfg
setup.py
versioneer.py
pyHMSA_matlab.egg-info/PKG-INFO
pyHMSA_matlab.egg-info/SOURCES.txt
pyHMSA_matlab.egg-info/dependency_links.txt
pyHMSA_matlab.egg-info/entry_points.txt
pyHMSA_matlab.egg-info/requires.txt
pyHMSA_matlab.egg-info/top_level.txt
pyHMSA_matlab.egg-info/zip-safe
pyhmsa_matlab/__init__.py
pyhmsa_matlab/_version.py
pyhmsa_matlab/fileformat/__init__.py
pyhmsa_matlab/fileformat/exporter/__init__.py
pyhmsa_matlab/fileformat/exporter/matlab.py
pyhmsa_matlab/fileformat/exporter/test_matlab.py