Metadata-Version: 1.1
Name: pyHMSA-matlab
Version: 0.1.0
Summary: UNKNOWN
Home-page: http://pyhmsa.readthedocs.org
Author: Philippe Pinard
Author-email: philippe.pinard@gmail.com
License: MIT
Keywords: microscopy microanalysis hmsa file format
Platform: UNKNOWN
Classifier: Development Status :: 4 - Beta
Classifier: Intended Audience :: Developers
Classifier: Intended Audience :: Science/Research
Classifier: Operating System :: OS Independent
Classifier: License :: OSI Approved :: MIT License
Classifier: Programming Language :: Python :: 2
Classifier: Programming Language :: Python :: 2.7
Classifier: Programming Language :: Python :: 3
Classifier: Programming Language :: Python :: 3.5
Classifier: Topic :: Scientific/Engineering :: Physics
